aardvark/__init__.py
aardvark/_config.py
aardvark/app.py
aardvark/manage.py
aardvark/model.py
aardvark/view.py
aardvark/updater/__init__.py
aardvark/utils/__init__.py
aardvark/utils/sqla_regex.py
aardvark-0.4.1.dist-info/LICENSE
aardvark-0.4.1.dist-info/METADATA
aardvark-0.4.1.dist-info/WHEEL
aardvark-0.4.1.dist-info/entry_points.txt
aardvark-0.4.1.dist-info/top_level.txt
aardvark-0.4.1.dist-info/RECORD
