Metadata-Version: 2.1
Name: aardvark
Version: 0.4.1
Summary: Multi-Account AWS IAM Access Advisor API
Home-page: https://github.com/Netflix-Skunkworks/aardvark
Author: Patrick Kelley, Travis McPeak, Patrick Sanders
Author-email: aardvark-maintainers@netflix.com
License: Apache 2.0
Requires-Python: >=3.8,<3.10
License-File: LICENSE
Requires-Dist: blinker
Requires-Dist: boto3
Requires-Dist: botocore
Requires-Dist: bunch
Requires-Dist: cloudaux >=1.8.0
Requires-Dist: Flask
Requires-Dist: Flask-RESTful
Requires-Dist: Flask-Script
Requires-Dist: Flask-SQLAlchemy >=2.5
Requires-Dist: SQLAlchemy
Requires-Dist: swag-client
Requires-Dist: pexpect >=4.2.1 ; extra == "tests"
Provides-Extra: tests
Requires-Dist: pexpect >=4.2.1 ; extra == 'tests'
